greeclimate/__init__.py
greeclimate/cipher.py
greeclimate/device.py
greeclimate/deviceinfo.py
greeclimate/discovery.py
greeclimate/exceptions.py
greeclimate/network.py
greeclimate/taskable.py
greeclimate-2.1.3.dist-info/licenses/LICENSE.txt
greeclimate-2.1.3.dist-info/METADATA
greeclimate-2.1.3.dist-info/WHEEL
greeclimate-2.1.3.dist-info/top_level.txt
greeclimate-2.1.3.dist-info/RECORD
