Metadata-Version: 2.4
Name: greeclimate
Version: 2.1.3
Summary: Discover, connect and control Gree based minisplit systems
Home-page: https://github.com/cmroche/greeclimate
Author: Clifford Roche
Author-email: 
Classifier: Programming Language :: Python :: 3
Classifier: License :: OSI Approved :: GNU General Public License v3 (GPLv3)
Classifier: Operating System :: OS Independent
Requires-Python: >=3.8
License-File: LICENSE.txt
Requires-Dist: netifaces
Requires-Dist: pycryptodome~=3.10
Dynamic: author
Dynamic: classifier
Dynamic: description
Dynamic: description-content-type
Dynamic: home-page
Dynamic: license-file
Dynamic: requires-dist
Dynamic: requires-python
Dynamic: summary
